{"_type":"export","__export_format":4,"__export_date":"2024-04-24T21:25:10.286Z","__export_source":"insomnia.desktop.app:v8.6.1","resources":[{"_id":"req_403a0f1f1ac04a469713f9b30a48f72b","parentId":"fld_a53b87a2d5724c809c60c3f62f5852d7","modified":1713993759528,"created":1713734859521,"url":"localhost:8080/simulation","name":"Simulation Create","description":"","method":"POST","body":{"mimeType":"application/json","text":"{\n\t\t\"cpf\": \"222.222.222-22\",\n\t\t\"requestedAmount\": 4000,\n\t\t\"numberInstallment\": 12\n}\n"},"parameters":[],"headers":[{"name":"Content-Type","value":"application/json"},{"name":"User-Agent","value":"insomnia/8.6.1"}],"authentication":{},"metaSortKey":-1713993730452,"isPrivate":false,"pathParameters":[],"settingStoreCookies":true,"settingSendCookies":true,"settingDisableRenderRequestBody":false,"settingEncodeUrl":true,"settingRebuildPath":true,"settingFollowRedirects":"global","_type":"request"},{"_id":"fld_a53b87a2d5724c809c60c3f62f5852d7","parentId":"wrk_scratchpad","modified":1713993184129,"created":1713993184129,"name":"Simulation","description":"","environment":{},"environmentPropertyOrder":null,"metaSortKey":-1713993184129,"_type":"request_group"},{"_id":"wrk_scratchpad","parentId":null,"modified":1713540440622,"created":1713540440622,"name":"Scratch Pad","description":"","scope":"collection","_type":"workspace"},{"_id":"req_4a2403d85f5b4ac09d22f741466d93c5","parentId":"fld_a53b87a2d5724c809c60c3f62f5852d7","modified":1713993765161,"created":1713993358078,"url":"localhost:8080/simulation","name":"Simulation Create With Invalid Cpf","description":"","method":"POST","body":{"mimeType":"application/json","text":"{\n\t\t\"cpf\": \"555.555.555-abc\",\n\t\t\"requestedAmount\": 500,\n\t\t\"numberInstallment\": 12\n}\n"},"parameters":[],"headers":[{"name":"Content-Type","value":"application/json"},{"name":"User-Agent","value":"insomnia/8.6.1"}],"authentication":{},"metaSortKey":-1713993730402,"isPrivate":false,"pathParameters":[],"settingStoreCookies":true,"settingSendCookies":true,"settingDisableRenderRequestBody":false,"settingEncodeUrl":true,"settingRebuildPath":true,"settingFollowRedirects":"global","_type":"request"},{"_id":"req_e9b3de132cdd4247b4c00db4680d38eb","parentId":"fld_a53b87a2d5724c809c60c3f62f5852d7","modified":1713993767189,"created":1713993381960,"url":"localhost:8080/simulation","name":"Simulation Create With Non Existing Cpf","description":"","method":"POST","body":{"mimeType":"application/json","text":"{\n\t\t\"cpf\": \"555.555.555-10\",\n\t\t\"requestedAmount\": 500,\n\t\t\"numberInstallment\": 12\n}\n"},"parameters":[],"headers":[{"name":"Content-Type","value":"application/json"},{"name":"User-Agent","value":"insomnia/8.6.1"}],"authentication":{},"metaSortKey":-1713993730377,"isPrivate":false,"pathParameters":[],"settingStoreCookies":true,"settingSendCookies":true,"settingDisableRenderRequestBody":false,"settingEncodeUrl":true,"settingRebuildPath":true,"settingFollowRedirects":"global","_type":"request"},{"_id":"req_303cf74d088343b5a72326496f76011a","parentId":"fld_a53b87a2d5724c809c60c3f62f5852d7","modified":1713993745638,"created":1713993546913,"url":"localhost:8080/simulation","name":"Simulation Create Without Number of Installments","description":"","method":"POST","body":{"mimeType":"application/json","text":"{\n\t\t\"cpf\": \"555.555.555-55\",\n\t\t\"requestedAmount\": 500,\n\t\t\"numberInstallment\": null\n}\n"},"parameters":[],"headers":[{"name":"Content-Type","value":"application/json"},{"name":"User-Agent","value":"insomnia/8.6.1"}],"authentication":{},"metaSortKey":-1713993730352,"isPrivate":false,"pathParameters":[],"settingStoreCookies":true,"settingSendCookies":true,"settingDisableRenderRequestBody":false,"settingEncodeUrl":true,"settingRebuildPath":true,"settingFollowRedirects":"global","_type":"request"},{"_id":"req_48e7a693438f4f5b8af3500155612a78","parentId":"fld_a53b87a2d5724c809c60c3f62f5852d7","modified":1713993742625,"created":1713993498746,"url":"localhost:8080/simulation","name":"Simulation Create Without Requested Amount","description":"","method":"POST","body":{"mimeType":"application/json","text":"{\n\t\t\"cpf\": \"555.555.555-55\",\n\t\t\"requestedAmount\": null,\n\t\t\"numberInstallment\": 12\n}\n"},"parameters":[],"headers":[{"name":"Content-Type","value":"application/json"},{"name":"User-Agent","value":"insomnia/8.6.1"}],"authentication":{},"metaSortKey":-1713993730252,"isPrivate":false,"pathParameters":[],"settingStoreCookies":true,"settingSendCookies":true,"settingDisableRenderRequestBody":false,"settingEncodeUrl":true,"settingRebuildPath":true,"settingFollowRedirects":"global","_type":"request"},{"_id":"req_719159f619c94cdcb376131b4cf0dbb3","parentId":"fld_a53b87a2d5724c809c60c3f62f5852d7","modified":1713993735598,"created":1713826800713,"url":"localhost:8080/simulation/id/1/cpf/222.222.222-22","name":"Simulation Get By Id And CPF","description":"","method":"GET","body":{},"parameters":[],"headers":[{"name":"User-Agent","value":"insomnia/8.6.1"}],"authentication":{},"metaSortKey":-1713993729952,"isPrivate":false,"pathParameters":[],"settingStoreCookies":true,"settingSendCookies":true,"settingDisableRenderRequestBody":false,"settingEncodeUrl":true,"settingRebuildPath":true,"settingFollowRedirects":"global","_type":"request"},{"_id":"req_90a0c37e6f2340ce8a48a441306e930b","parentId":"fld_a53b87a2d5724c809c60c3f62f5852d7","modified":1713993732316,"created":1713735527929,"url":"localhost:8080/simulation/all","name":"Simulation Get All","description":"","method":"GET","body":{},"parameters":[],"headers":[{"name":"User-Agent","value":"insomnia/8.6.1"}],"authentication":{},"metaSortKey":-1713993729852,"isPrivate":false,"pathParameters":[],"settingStoreCookies":true,"settingSendCookies":true,"settingDisableRenderRequestBody":false,"settingEncodeUrl":true,"settingRebuildPath":true,"settingFollowRedirects":"global","_type":"request"},{"_id":"req_b489e224dfab424381dea799fc2172c6","parentId":"fld_d52d2a85e4a94030bc9ab9fcd4eb6b4a","modified":1713993777053,"created":1713730030656,"url":"localhost:8082/custody","name":"Custody Create","description":"","method":"POST","body":{"mimeType":"application/json","text":"{\n\t\t\"simulationId\": \"1\"\n\t}"},"parameters":[],"headers":[{"name":"Content-Type","value":"application/json"},{"name":"User-Agent","value":"insomnia/8.6.1"}],"authentication":{},"metaSortKey":-1713993145358,"isPrivate":false,"pathParameters":[],"settingStoreCookies":true,"settingSendCookies":true,"settingDisableRenderRequestBody":false,"settingEncodeUrl":true,"settingRebuildPath":true,"settingFollowRedirects":"global","_type":"request"},{"_id":"fld_d52d2a85e4a94030bc9ab9fcd4eb6b4a","parentId":"wrk_scratchpad","modified":1713992981101,"created":1713992981101,"name":"Custody","description":"","environment":{},"environmentPropertyOrder":null,"metaSortKey":-1713992981101,"_type":"request_group"},{"_id":"req_22847f9138f64d8aae26fce622888980","parentId":"fld_d52d2a85e4a94030bc9ab9fcd4eb6b4a","modified":1713993808259,"created":1713993079146,"url":"localhost:8082/custody","name":"Custody Create With Invalid Simulation Id","description":"","method":"POST","body":{"mimeType":"application/json","text":"{\n\t\t\"simulationId\": \"\"\n\t}"},"parameters":[],"headers":[{"name":"Content-Type","value":"application/json"},{"name":"User-Agent","value":"insomnia/8.6.1"}],"authentication":{},"metaSortKey":-1713993145308,"isPrivate":false,"pathParameters":[],"settingStoreCookies":true,"settingSendCookies":true,"settingDisableRenderRequestBody":false,"settingEncodeUrl":true,"settingRebuildPath":true,"settingFollowRedirects":"global","_type":"request"},{"_id":"req_4625175750c4493ebd6a253e7bde38c5","parentId":"fld_d52d2a85e4a94030bc9ab9fcd4eb6b4a","modified":1713993169399,"created":1713731878711,"url":"localhost:8082/custody/all","name":"Custody Get All","description":"","method":"GET","body":{},"parameters":[],"headers":[{"name":"User-Agent","value":"insomnia/8.6.1"}],"authentication":{},"metaSortKey":-1713993145258,"isPrivate":false,"pathParameters":[],"settingStoreCookies":true,"settingSendCookies":true,"settingDisableRenderRequestBody":false,"settingEncodeUrl":true,"settingRebuildPath":true,"settingFollowRedirects":"global","_type":"request"},{"_id":"req_a03e9c8aeb1a44a7bdf0bf218c8de998","parentId":"fld_37abf2668867450f99ee0f72d4a6d0d7","modified":1713992769805,"created":1713540475289,"url":"localhost:8081/customers/all","name":"Customers Get All","description":"","method":"GET","body":{},"parameters":[],"headers":[{"name":"User-Agent","value":"insomnia/8.6.1"}],"authentication":{},"metaSortKey":-1713992765553,"isPrivate":false,"pathParameters":[],"settingStoreCookies":true,"settingSendCookies":true,"settingDisableRenderRequestBody":false,"settingEncodeUrl":true,"settingRebuildPath":true,"settingFollowRedirects":"global","_type":"request"},{"_id":"fld_37abf2668867450f99ee0f72d4a6d0d7","parentId":"wrk_scratchpad","modified":1713992739017,"created":1713992739017,"name":"Customers","description":"","environment":{},"environmentPropertyOrder":null,"metaSortKey":-1713992739018,"_type":"request_group"},{"_id":"req_b2d91e82d78543b3a89fe8c1ddde3ab0","parentId":"fld_37abf2668867450f99ee0f72d4a6d0d7","modified":1713992782859,"created":1713824622368,"url":"localhost:8081/customers/111.111.111-11","name":"Customers Get By CPF","description":"","method":"GET","body":{},"parameters":[],"headers":[{"name":"User-Agent","value":"insomnia/8.6.1"}],"authentication":{},"metaSortKey":-1713992765453,"isPrivate":false,"pathParameters":[],"settingStoreCookies":true,"settingSendCookies":true,"settingDisableRenderRequestBody":false,"settingEncodeUrl":true,"settingRebuildPath":true,"settingFollowRedirects":"global","_type":"request"},{"_id":"req_d247cdb3639d49b78969d0487e0b8184","parentId":"fld_37abf2668867450f99ee0f72d4a6d0d7","modified":1713992807968,"created":1713992801796,"url":"localhost:8081/customers/111.111.111-abc","name":"Customers Get By Invalid CPF","description":"","method":"GET","body":{},"parameters":[],"headers":[{"name":"User-Agent","value":"insomnia/8.6.1"}],"authentication":{},"metaSortKey":-1713861398054.5,"isPrivate":false,"pathParameters":[],"settingStoreCookies":true,"settingSendCookies":true,"settingDisableRenderRequestBody":false,"settingEncodeUrl":true,"settingRebuildPath":true,"settingFollowRedirects":"global","_type":"request"},{"_id":"req_1dfc8f1557ba499d8f030220042c259f","parentId":"fld_37abf2668867450f99ee0f72d4a6d0d7","modified":1713992949848,"created":1713992944743,"url":"localhost:8081/customers/111.111.111-50","name":"Customers Get By Non Exixting CPF","description":"","method":"GET","body":{},"parameters":[],"headers":[{"name":"User-Agent","value":"insomnia/8.6.1"}],"authentication":{},"metaSortKey":-1713795714355.25,"isPrivate":false,"pathParameters":[],"settingStoreCookies":true,"settingSendCookies":true,"settingDisableRenderRequestBody":false,"settingEncodeUrl":true,"settingRebuildPath":true,"settingFollowRedirects":"global","_type":"request"},{"_id":"env_99d30891da4bdcebc63947a8fc17f076de878684","parentId":"wrk_scratchpad","modified":1713540466779,"created":1713540466779,"name":"Base Environment","data":{},"dataPropertyOrder":null,"color":null,"isPrivate":false,"metaSortKey":1713540466779,"_type":"environment"},{"_id":"jar_99d30891da4bdcebc63947a8fc17f076de878684","parentId":"wrk_scratchpad","modified":1713540466793,"created":1713540466793,"name":"Default Jar","cookies":[],"_type":"cookie_jar"}]}